{
    "itemprop": [
        {
            "content": "The Verve - Bitter Sweet Symphony (Official Music Video)",
            "itemprop": "name"
        },
        {
            "content": "REMASTERED IN HD! UP TO 4K!!Check out the official music video for \"Better Sweet Symphony\" by The VerveDiscover more about this classic song here: https://ww...",
            "itemprop": "description"
        },
        {
            "content": "False",
            "itemprop": "paid"
        },
        {
            "content": "UCY9j66iGshbnQhO7ggwRyhA",
            "itemprop": "channelId"
        },
        {
            "content": "1lyu1KKwC74",
            "itemprop": "videoId"
        },
        {
            "content": "PT4M36S",
            "itemprop": "duration"
        },
        {
            "content": "False",
            "itemprop": "unlisted"
        },
        {
            "content": "1280",
            "itemprop": "width"
        },
        {
            "content": "720",
            "itemprop": "height"
        },
        {
            "content": "HTML5 Flash",
            "itemprop": "playerType"
        },
        {
            "content": "1280",
            "itemprop": "width"
        },
        {
            "content": "720",
            "itemprop": "height"
        },
        {
            "content": "true",
            "itemprop": "isFamilyFriendly"
        },
        {
            "content": "AD,AE,AG,AI,AL,AM,AO,AQ,AR,AS,AT,AU,AW,AZ,BA,BB,BD,BE,BF,BG,BH,BI,BJ,BN,BO,BR,BS,BT,BV,BW,BY,BZ,CA,CC,CD,CF,CG,CH,CI,CK,CL,CM,CN,CO,CR,CU,CV,CX,CY,CZ,DE,DJ,DK,DM,DO,DZ,EC,EE,EG,EH,ER,ES,ET,FI,FJ,FK,FM,FO,FR,GA,GB,GD,GE,GF,GH,GI,GM,GN,GP,GQ,GR,GS,GT,GU,GW,GY,HK,HM,HN,HR,HT,HU,ID,IE,IL,IN,IO,IQ,IR,IS,IT,JM,JO,JP,KE,KH,KI,KM,KN,KP,KR,KW,KY,KZ,LA,LB,LC,LI,LK,LR,LS,LT,LU,LV,LY,MA,MC,MD,MG,MH,ML,MN,MO,MP,MQ,MR,MS,MT,MU,MV,MW,MX,MY,MZ,NA,NC,NE,NF,NG,NI,NL,NO,NP,NR,NU,NZ,OM,PA,PE,PF,PG,PH,PK,PL,PM,PN,PR,PT,PW,PY,QA,RE,RO,RU,RW,SA,SB,SC,SD,SE,SG,SH,SI,SJ,SK,SL,SM,SN,SO,SR,ST,SV,SY,SZ,TC,TD,TF,TG,TH,TJ,TK,TL,TM,TN,TO,TR,TT,TV,TW,TZ,UA,UG,UM,US,UY,UZ,VC,VE,VG,VI,VN,VU,WF,WS,YE,YT,ZA,ZM,ZW",
            "itemprop": "regionsAllowed"
        },
        {
            "content": "760336472",
            "itemprop": "interactionCount"
        },
        {
            "content": "2009-02-28",
            "itemprop": "datePublished"
        },
        {
            "content": "2009-02-28",
            "itemprop": "uploadDate"
        },
        {
            "content": "Music",
            "itemprop": "genre"
        }
    ],
    "name": [
        {
            "content": "rgba(255, 255, 255, 0.98)",
            "name": "theme-color"
        },
        {
            "content": "The Verve - Bitter Sweet Symphony (Official Music Video)",
            "name": "title"
        },
        {
            "content": "REMASTERED IN HD! UP TO 4K!!Check out the official music video for \"Better Sweet Symphony\" by The VerveDiscover more about this classic song here: https://ww...",
            "name": "description"
        },
        {
            "content": "the verve, bittersweet symphony, the verve bittersweet symphony video, the verve bittersweet symphony, bittersweet symphony the verve, the verve karaoke, bittersweet symphony acoustic, bittersweet symphony lyrics, symphony instrumental, bittersweet symphony live, bittersweet symphony official video, bittersweet symphony cover, THE VERVE BITTER SWEET SYMPHONY, BITTER SWEET SYMPHONY, BITTER SWEET SYMPHONY THE VERVE, BITTER, SWEET, SYMPHONY",
            "name": "keywords"
        },
        {
            "content": "player",
            "name": "twitter:card"
        },
        {
            "content": "@youtube",
            "name": "twitter:site"
        },
        {
            "content": "https://www.youtube.com/watch?v=1lyu1KKwC74",
            "name": "twitter:url"
        },
        {
            "content": "The Verve - Bitter Sweet Symphony (Official Music Video)",
            "name": "twitter:title"
        },
        {
            "content": "REMASTERED IN HD! UP TO 4K!!Check out the official music video for \"Better Sweet Symphony\" by The VerveDiscover more about this classic song here: https://ww...",
            "name": "twitter:description"
        },
        {
            "content": "https://i.ytimg.com/vi/1lyu1KKwC74/maxresdefault.jpg",
            "name": "twitter:image"
        },
        {
            "content": "YouTube",
            "name": "twitter:app:name:iphone"
        },
        {
            "content": "544007664",
            "name": "twitter:app:id:iphone"
        },
        {
            "content": "YouTube",
            "name": "twitter:app:name:ipad"
        },
        {
            "content": "544007664",
            "name": "twitter:app:id:ipad"
        },
        {
            "content": "vnd.youtube://www.youtube.com/watch?v=1lyu1KKwC74&feature=applinks",
            "name": "twitter:app:url:iphone"
        },
        {
            "content": "vnd.youtube://www.youtube.com/watch?v=1lyu1KKwC74&feature=applinks",
            "name": "twitter:app:url:ipad"
        },
        {
            "content": "YouTube",
            "name": "twitter:app:name:googleplay"
        },
        {
            "content": "com.google.android.youtube",
            "name": "twitter:app:id:googleplay"
        },
        {
            "content": "https://www.youtube.com/watch?v=1lyu1KKwC74",
            "name": "twitter:app:url:googleplay"
        },
        {
            "content": "https://www.youtube.com/embed/1lyu1KKwC74",
            "name": "twitter:player"
        },
        {
            "content": "1280",
            "name": "twitter:player:width"
        },
        {
            "content": "720",
            "name": "twitter:player:height"
        }
    ],
    "property": [
        {
            "content": "YouTube",
            "property": "og:site_name"
        },
        {
            "content": "https://www.youtube.com/watch?v=1lyu1KKwC74",
            "property": "og:url"
        },
        {
            "content": "The Verve - Bitter Sweet Symphony (Official Music Video)",
            "property": "og:title"
        },
        {
            "content": "https://i.ytimg.com/vi/1lyu1KKwC74/maxresdefault.jpg",
            "property": "og:image"
        },
        {
            "content": "1280",
            "property": "og:image:width"
        },
        {
            "content": "720",
            "property": "og:image:height"
        },
        {
            "content": "REMASTERED IN HD! UP TO 4K!!Check out the official music video for \"Better Sweet Symphony\" by The VerveDiscover more about this classic song here: https://ww...",
            "property": "og:description"
        },
        {
            "content": "544007664",
            "property": "al:ios:app_store_id"
        },
        {
            "content": "YouTube",
            "property": "al:ios:app_name"
        },
        {
            "content": "vnd.youtube://www.youtube.com/watch?v=1lyu1KKwC74&feature=applinks",
            "property": "al:ios:url"
        },
        {
            "content": "vnd.youtube://www.youtube.com/watch?v=1lyu1KKwC74&feature=applinks",
            "property": "al:android:url"
        },
        {
            "content": "http://www.youtube.com/watch?v=1lyu1KKwC74&feature=applinks",
            "property": "al:web:url"
        },
        {
            "content": "video.other",
            "property": "og:type"
        },
        {
            "content": "https://www.youtube.com/embed/1lyu1KKwC74",
            "property": "og:video:url"
        },
        {
            "content": "https://www.youtube.com/embed/1lyu1KKwC74",
            "property": "og:video:secure_url"
        },
        {
            "content": "text/html",
            "property": "og:video:type"
        },
        {
            "content": "1280",
            "property": "og:video:width"
        },
        {
            "content": "720",
            "property": "og:video:height"
        },
        {
            "content": "YouTube",
            "property": "al:android:app_name"
        },
        {
            "content": "com.google.android.youtube",
            "property": "al:android:package"
        },
        {
            "content": "the verve",
            "property": "og:video:tag"
        },
        {
            "content": "bittersweet symphony",
            "property": "og:video:tag"
        },
        {
            "content": "the verve bittersweet symphony video",
            "property": "og:video:tag"
        },
        {
            "content": "the verve bittersweet symphony",
            "property": "og:video:tag"
        },
        {
            "content": "bittersweet symphony the verve",
            "property": "og:video:tag"
        },
        {
            "content": "the verve karaoke",
            "property": "og:video:tag"
        },
        {
            "content": "bittersweet symphony acoustic",
            "property": "og:video:tag"
        },
        {
            "content": "bittersweet symphony lyrics",
            "property": "og:video:tag"
        },
        {
            "content": "symphony instrumental",
            "property": "og:video:tag"
        },
        {
            "content": "bittersweet symphony live",
            "property": "og:video:tag"
        },
        {
            "content": "bittersweet symphony official video",
            "property": "og:video:tag"
        },
        {
            "content": "bittersweet symphony cover",
            "property": "og:video:tag"
        },
        {
            "content": "THE VERVE BITTER SWEET SYMPHONY",
            "property": "og:video:tag"
        },
        {
            "content": "BITTER SWEET SYMPHONY",
            "property": "og:video:tag"
        },
        {
            "content": "BITTER SWEET SYMPHONY THE VERVE",
            "property": "og:video:tag"
        },
        {
            "content": "BITTER",
            "property": "og:video:tag"
        },
        {
            "content": "SWEET",
            "property": "og:video:tag"
        },
        {
            "content": "SYMPHONY",
            "property": "og:video:tag"
        },
        {
            "content": "87741124305",
            "property": "fb:app_id"
        }
    ]
}