{
    "itemprop": [
        {
            "content": "Elvis Presley - Can't Help Falling In Love (Official Audio)",
            "itemprop": "name"
        },
        {
            "content": "\"Can't Help Falling In Love\" by Elvis PresleyListen to Elvis Presley: https://Elvis.lnk.to/_listenYDSubscribe to the official Elvis Presley YouTube Channel: ...",
            "itemprop": "description"
        },
        {
            "content": "False",
            "itemprop": "paid"
        },
        {
            "content": "UCSEmH1YyFWltSBYkfLMtkcg",
            "itemprop": "channelId"
        },
        {
            "content": "vGJTaP6anOU",
            "itemprop": "videoId"
        },
        {
            "content": "PT3M1S",
            "itemprop": "duration"
        },
        {
            "content": "False",
            "itemprop": "unlisted"
        },
        {
            "content": "1280",
            "itemprop": "width"
        },
        {
            "content": "720",
            "itemprop": "height"
        },
        {
            "content": "HTML5 Flash",
            "itemprop": "playerType"
        },
        {
            "content": "1280",
            "itemprop": "width"
        },
        {
            "content": "720",
            "itemprop": "height"
        },
        {
            "content": "true",
            "itemprop": "isFamilyFriendly"
        },
        {
            "content": "AD,AE,AF,AG,AI,AL,AM,AO,AQ,AR,AS,AT,AU,AW,AX,AZ,BA,BB,BD,BE,BF,BG,BH,BI,BJ,BL,BM,BN,BO,BQ,BR,BS,BT,BV,BW,BY,BZ,CA,CC,CD,CF,CG,CH,CI,CK,CL,CM,CN,CO,CR,CU,CV,CW,CX,CY,CZ,DE,DJ,DK,DM,DO,DZ,EC,EE,EG,EH,ER,ES,ET,FI,FJ,FK,FM,FO,FR,GA,GB,GD,GE,GF,GG,GH,GI,GL,GM,GN,GP,GQ,GR,GS,GT,GU,GW,GY,HK,HM,HN,HR,HT,HU,ID,IE,IL,IM,IN,IO,IQ,IR,IS,IT,JE,JM,JO,JP,KE,KG,KH,KI,KM,KN,KP,KR,KW,KY,KZ,LA,LB,LC,LI,LK,LR,LS,LT,LU,LV,LY,MA,MC,MD,ME,MF,MG,MH,MK,ML,MM,MN,MO,MP,MQ,MR,MS,MT,MU,MV,MW,MX,MY,MZ,NA,NC,NE,NF,NG,NI,NL,NO,NP,NR,NU,NZ,OM,PA,PE,PF,PG,PH,PK,PL,PM,PN,PR,PS,PT,PW,PY,QA,RE,RO,RS,RU,RW,SA,SB,SC,SD,SE,SG,SH,SI,SJ,SK,SL,SM,SN,SO,SR,SS,ST,SV,SX,SY,SZ,TC,TD,TF,TG,TH,TJ,TK,TL,TM,TN,TO,TR,TT,TV,TW,TZ,UA,UG,UM,US,UY,UZ,VA,VC,VE,VG,VI,VN,VU,WF,WS,YE,YT,ZA,ZM,ZW",
            "itemprop": "regionsAllowed"
        },
        {
            "content": "318010869",
            "itemprop": "interactionCount"
        },
        {
            "content": "2013-04-23",
            "itemprop": "datePublished"
        },
        {
            "content": "2013-04-23",
            "itemprop": "uploadDate"
        },
        {
            "content": "Music",
            "itemprop": "genre"
        }
    ],
    "name": [
        {
            "content": "rgba(255, 255, 255, 0.98)",
            "name": "theme-color"
        },
        {
            "content": "Elvis Presley - Can't Help Falling In Love (Official Audio)",
            "name": "title"
        },
        {
            "content": "\"Can't Help Falling In Love\" by Elvis PresleyListen to Elvis Presley: https://Elvis.lnk.to/_listenYDSubscribe to the official Elvis Presley YouTube Channel: ...",
            "name": "description"
        },
        {
            "content": "elvis presley, elvis presley can't help falling in love, can't help falling in love with you, can't help falling in love, falling in love with you, i can't help falling in love with you, elvis, wise men say only fools rush in, falling in love, cant help falling in love with you twenty one pilots lyrics, elvis presley falling in love with you, cant help falling in love with you, pop music, Oldies music, Suspicious Minds, stand by me, Put, Your",
            "name": "keywords"
        },
        {
            "content": "player",
            "name": "twitter:card"
        },
        {
            "content": "@youtube",
            "name": "twitter:site"
        },
        {
            "content": "https://www.youtube.com/watch?v=vGJTaP6anOU",
            "name": "twitter:url"
        },
        {
            "content": "Elvis Presley - Can't Help Falling In Love (Official Audio)",
            "name": "twitter:title"
        },
        {
            "content": "\"Can't Help Falling In Love\" by Elvis PresleyListen to Elvis Presley: https://Elvis.lnk.to/_listenYDSubscribe to the official Elvis Presley YouTube Channel: ...",
            "name": "twitter:description"
        },
        {
            "content": "https://i.ytimg.com/vi/vGJTaP6anOU/maxresdefault.jpg",
            "name": "twitter:image"
        },
        {
            "content": "YouTube",
            "name": "twitter:app:name:iphone"
        },
        {
            "content": "544007664",
            "name": "twitter:app:id:iphone"
        },
        {
            "content": "YouTube",
            "name": "twitter:app:name:ipad"
        },
        {
            "content": "544007664",
            "name": "twitter:app:id:ipad"
        },
        {
            "content": "vnd.youtube://www.youtube.com/watch?v=vGJTaP6anOU&feature=applinks",
            "name": "twitter:app:url:iphone"
        },
        {
            "content": "vnd.youtube://www.youtube.com/watch?v=vGJTaP6anOU&feature=applinks",
            "name": "twitter:app:url:ipad"
        },
        {
            "content": "YouTube",
            "name": "twitter:app:name:googleplay"
        },
        {
            "content": "com.google.android.youtube",
            "name": "twitter:app:id:googleplay"
        },
        {
            "content": "https://www.youtube.com/watch?v=vGJTaP6anOU",
            "name": "twitter:app:url:googleplay"
        },
        {
            "content": "https://www.youtube.com/embed/vGJTaP6anOU",
            "name": "twitter:player"
        },
        {
            "content": "1280",
            "name": "twitter:player:width"
        },
        {
            "content": "720",
            "name": "twitter:player:height"
        }
    ],
    "property": [
        {
            "content": "YouTube",
            "property": "og:site_name"
        },
        {
            "content": "https://www.youtube.com/watch?v=vGJTaP6anOU",
            "property": "og:url"
        },
        {
            "content": "Elvis Presley - Can't Help Falling In Love (Official Audio)",
            "property": "og:title"
        },
        {
            "content": "https://i.ytimg.com/vi/vGJTaP6anOU/maxresdefault.jpg",
            "property": "og:image"
        },
        {
            "content": "1280",
            "property": "og:image:width"
        },
        {
            "content": "720",
            "property": "og:image:height"
        },
        {
            "content": "\"Can't Help Falling In Love\" by Elvis PresleyListen to Elvis Presley: https://Elvis.lnk.to/_listenYDSubscribe to the official Elvis Presley YouTube Channel: ...",
            "property": "og:description"
        },
        {
            "content": "544007664",
            "property": "al:ios:app_store_id"
        },
        {
            "content": "YouTube",
            "property": "al:ios:app_name"
        },
        {
            "content": "vnd.youtube://www.youtube.com/watch?v=vGJTaP6anOU&feature=applinks",
            "property": "al:ios:url"
        },
        {
            "content": "vnd.youtube://www.youtube.com/watch?v=vGJTaP6anOU&feature=applinks",
            "property": "al:android:url"
        },
        {
            "content": "http://www.youtube.com/watch?v=vGJTaP6anOU&feature=applinks",
            "property": "al:web:url"
        },
        {
            "content": "video.other",
            "property": "og:type"
        },
        {
            "content": "https://www.youtube.com/embed/vGJTaP6anOU",
            "property": "og:video:url"
        },
        {
            "content": "https://www.youtube.com/embed/vGJTaP6anOU",
            "property": "og:video:secure_url"
        },
        {
            "content": "text/html",
            "property": "og:video:type"
        },
        {
            "content": "1280",
            "property": "og:video:width"
        },
        {
            "content": "720",
            "property": "og:video:height"
        },
        {
            "content": "YouTube",
            "property": "al:android:app_name"
        },
        {
            "content": "com.google.android.youtube",
            "property": "al:android:package"
        },
        {
            "content": "elvis presley",
            "property": "og:video:tag"
        },
        {
            "content": "elvis presley can't help falling in love",
            "property": "og:video:tag"
        },
        {
            "content": "can't help falling in love with you",
            "property": "og:video:tag"
        },
        {
            "content": "can't help falling in love",
            "property": "og:video:tag"
        },
        {
            "content": "falling in love with you",
            "property": "og:video:tag"
        },
        {
            "content": "i can't help falling in love with you",
            "property": "og:video:tag"
        },
        {
            "content": "elvis",
            "property": "og:video:tag"
        },
        {
            "content": "wise men say only fools rush in",
            "property": "og:video:tag"
        },
        {
            "content": "falling in love",
            "property": "og:video:tag"
        },
        {
            "content": "cant help falling in love with you twenty one pilots lyrics",
            "property": "og:video:tag"
        },
        {
            "content": "elvis presley falling in love with you",
            "property": "og:video:tag"
        },
        {
            "content": "cant help falling in love with you",
            "property": "og:video:tag"
        },
        {
            "content": "pop music",
            "property": "og:video:tag"
        },
        {
            "content": "Oldies music",
            "property": "og:video:tag"
        },
        {
            "content": "Suspicious Minds",
            "property": "og:video:tag"
        },
        {
            "content": "stand by me",
            "property": "og:video:tag"
        },
        {
            "content": "Put",
            "property": "og:video:tag"
        },
        {
            "content": "Your",
            "property": "og:video:tag"
        },
        {
            "content": "87741124305",
            "property": "fb:app_id"
        }
    ]
}